mastodon_to_sqlite/__init__.py
mastodon_to_sqlite/cli.py
mastodon_to_sqlite/client.py
mastodon_to_sqlite/service.py
mastodon_to_sqlite-0.2.1.dist-info/LICENSE
mastodon_to_sqlite-0.2.1.dist-info/METADATA
mastodon_to_sqlite-0.2.1.dist-info/WHEEL
mastodon_to_sqlite-0.2.1.dist-info/entry_points.txt
mastodon_to_sqlite-0.2.1.dist-info/RECORD
