Metadata-Version: 2.1
Name: mastodon-to-sqlite
Version: 0.2.1
Summary: Save data from Mastodon to a SQLite database
Home-page: https://github.com/myles/mastodon-to-sqlite
License: Apache-2.0
Keywords: mastodon,sqlite,dogsheep
Author: Myles Braithwaite
Author-email: me@mylesbraithwaite.com
Requires-Python: >=3.9,<4.0
Classifier: License :: OSI Approved :: Apache Software License
Classifier: Programming Language :: Python :: 3
Classifier: Programming Language :: Python :: 3.9
Classifier: Programming Language :: Python :: 3.10
Classifier: Programming Language :: Python :: 3.11
Classifier: Programming Language :: Python :: 3.12
Requires-Dist: click (>=8.1.7,<9.0.0)
Requires-Dist: requests (>=2.31.0,<3.0.0)
Requires-Dist: sqlite-utils (>=3.36,<4.0)
Project-URL: Repository, https://github.com/myles/mastodon-to-sqlite
